verysimplemodule_erlanny/__init__.py
verysimplemodule_erlanny/add.py
verysimplemodule_erlanny/subtract.py
verysimplemodule_erlanny/extra/__init__.py
verysimplemodule_erlanny/extra/divide.py
verysimplemodule_erlanny/extra/multiple.py
verysimplemodule_erlanny-0.0.2.dist-info/METADATA
verysimplemodule_erlanny-0.0.2.dist-info/WHEEL
verysimplemodule_erlanny-0.0.2.dist-info/top_level.txt
verysimplemodule_erlanny-0.0.2.dist-info/RECORD
